LICENSE
README.md
setup.py
AzShell/__init__.py
AzShell/main.py
AzShell/commands/__init__.py
AzShell/commands/applications.py
AzShell/commands/auth.py
AzShell/commands/authmethods.py
AzShell/commands/chats.py
AzShell/commands/devices.py
AzShell/commands/domains.py
AzShell/commands/files.py
AzShell/commands/groups.py
AzShell/commands/messages.py
AzShell/commands/policies.py
AzShell/commands/roles.py
AzShell/commands/subscriptions.py
AzShell/commands/users.py
AzShell/commands/vaults.py
AzShell/commands/vms.py
AzShell/utils/__init__.py
AzShell/utils/constants.py
AzShell/utils/request.py
azshell.egg-info/PKG-INFO
azshell.egg-info/SOURCES.txt
azshell.egg-info/dependency_links.txt
azshell.egg-info/entry_points.txt
azshell.egg-info/requires.txt
azshell.egg-info/top_level.txt