Metadata-Version: 2.1
Name: azshell
Version: 1.2.1
Summary: Azure APIs enumeration and abuse
Home-page: https://github.com/vifreex/AzShell
Author: Víctor Rodríguez
Author-email: vifreex@protonmail.com
Classifier: Programming Language :: Python :: 3
Classifier: License :: OSI Approved :: GNU General Public License v3 (GPLv3)
License-File: LICENSE
